fistbump/__init__.py
fistbump/__main__.py
fistbump/fistbump.py
fistbump/version.txt
fistbump-1.5.0.dist-info/METADATA
fistbump-1.5.0.dist-info/WHEEL
fistbump-1.5.0.dist-info/entry_points.txt
fistbump-1.5.0.dist-info/top_level.txt
fistbump-1.5.0.dist-info/RECORD
