Metadata-Version: 2.2
Name: fistbump
Version: 1.5.0
Summary: fistbump
Classifier: Operating System :: OS Independent
Classifier: Programming Language :: Python
Classifier: Programming Language :: Python :: 3.10
Classifier: Programming Language :: Python :: 3.11
Requires-Python: >=3.10
Requires-Dist: semver
